momentchi2/__init__.py
momentchi2/methods.py
momentchi2/utilities.py
momentchi2-0.1.8.dist-info/LICENSE
momentchi2-0.1.8.dist-info/METADATA
momentchi2-0.1.8.dist-info/WHEEL
momentchi2-0.1.8.dist-info/top_level.txt
momentchi2-0.1.8.dist-info/RECORD
