Metadata-Version: 2.1
Name: momentchi2
Version: 0.1.8
Summary: A collection of methods for computing the cdf of a weighted sum of chi-squared random variables.
Home-page: https://github.com/pypa/momentchi2
Author: Dean Bodenham
Author-email: deanbodenhampkgs@gmail.com
License: UNKNOWN
Platform: UNKNOWN
Classifier: Programming Language :: Python :: 3
Classifier: License :: OSI Approved :: MIT License
Classifier: Operating System :: OS Independent
Requires-Python: >=3.6
License-File: LICENSE
